Workbook
Name CPI_Year: CPI!$A$6:$A$70
Name CPI_Index: CPI!$D$6:$D$70
Name Q_Date: Quarterly!$A$5:$A$294
Name Q_Year: Quarterly!$B$5:$B$294
Name Q_Label: Quarterly!$D$5:$D$294
Name Q_Price: Quarterly!$E$5:$E$294
Name Q_Real: Quarterly!$H$5:$H$294
Name Q_Fall: Quarterly!$N$5:$N$294
Name Q_Diff: Quarterly!$L$5:$L$294
Name A_Year: Annual!$A$5:$A$69
Name A_Price: Annual!$B$5:$B$69
Name A_Real: Annual!$C$5:$C$69
Name BaseYear: Dashboard!$C$5

Sheet About
B2: Are UK houses really more expensive?
B3: Nationwide average house prices since 1953, in cash and after inflation. Every number is a live formula over the raw data.
B5: How to use
B6: Dashboard | C6: Pick a base year (yellow cell). Every real price in the workbook is restated in that year's pounds.
B7: Mortgage | C7: Compare the monthly cost of the average house in two quarters. Change the deposit, term and interest rates (yellow cells).
B8: Colour code | C8: Blue text in a yellow cell: an input you can change. Black: a formula. Green: a value pulled from another sheet.
B10: Sheet map
B11: Dashboard | C11: Headline figures, charts and the biggest real-terms falls.
B12: Mortgage | C12: Monthly repayment then vs now, and a rate x deposit sensitivity grid (PMT).
B13: Annual | C13: One row per year: average price in cash and in base-year pounds, inflation, growth.
B14: Decades | C14: Growth per decade, in cash and real terms, with compound annual rates.
B15: Quarterly | C15: One row per Nationwide quarter: real price, year-on-year change, running real peak and fall from peak.
B16: CPI | C16: UK inflation each year from the World Bank, chained into a price index and rebased to the base year.
B17: Checks | C17: Reconciliation tests. The Dashboard shows whether they all pass.
B18: Raw_Nationwide | C18: Nationwide house price series exactly as published (datasets/house-prices-uk).
B19: Raw_CPI | C19: World Bank consumer price data for every country, exactly as published (datasets/cpi).
B21: Sources
B22: House prices | C22: Nationwide Building Society, UK house prices since 1952 (quarterly average price, all houses and new houses), via github.com/datasets/house-prices-uk (ODC PDDL 1.0).
B23: Inflation | C23: World Bank, consumer prices for the United Kingdom, via github.com/datasets/cpi (ODC PDDL 1.0).
B25: Notes and data quality
B26: CPI values | C26: The CPI file's metadata describes an index with 2005 = 100, but the values are annual % changes (UK 1975 = 24.2, 2024 = 3.3). The workbook treats them as annual inflation and chains them into an index (1959 = 100).
B27: Annual deflator | C27: Inflation is annual, so every quarter in a year is deflated by that year's average price level.
B28: Coverage | C28: Real prices run from 1960 to 2024, the years with inflation data. Quarters after 2024 show cash prices only.
B29: Methodology | C29: Nationwide's method changed over time: simple averages to 1959, floor-area weighting 1960-73, a regression-based mix adjustment from 1983. Long-run comparisons are approximate.
B30: Quarter labels | C30: Nationwide dates its quarters in February, May, August and November; these are labelled Q1 to Q4.
B31: Not included | C31: Earnings, so this is not an affordability ratio; and actual mortgage rates, which you enter yourself on the Mortgage sheet.
B33: Built by Qais Adeniji-Bello · github.com/QaisBello/uk-house-prices-excel

Sheet Dashboard
B2: Are UK houses really more expensive?
B3: Nationwide average house price, 1953-2025, in cash and in base-year pounds (after inflation).
B5: Base year (pick a year) | C5: 2024 | E5: Checks | F5: =IF(COUNTIF(Checks!C:C,"FAIL")=0,"All "&COUNTIF(Checks!C:C,"PASS")&" pass","FAILURES: see Checks")
B7: Latest average price | E7: Cash price, 1960 to latest | H7: Real price, 1960 to 2024
B8: =INDEX(Q_Price,MATCH(9.99E+307,Q_Price)) | E8: =INDEX(Q_Price,MATCH(9.99E+307,Q_Price))/INDEX(A_Price,1) | H8: =INDEX(A_Real,MATCH(2024,A_Year,0))/INDEX(A_Real,1)
B9: ="Nationwide, "&INDEX(Q_Label,MATCH(9.99E+307,Q_Price)) | E9: ="from "&TEXT(INDEX(A_Price,1),"£#,##0")&" (1960 average)" | H9: ="in "&BaseYear&" pounds: "&TEXT(INDEX(A_Real,1),"£#,##0")&" to "&TEXT(INDEX(A_Real,ROWS(A_Real)),"£#,##0")
B11: Real growth a year | E11: Inflation a year | H11: Biggest real fall from a peak
B12: =(INDEX(A_Real,ROWS(A_Real))/INDEX(A_Real,1))^(1/(2024-1960))-1 | E12: =(INDEX(CPI!$C:$C,MATCH(2024,CPI!$A:$A,0))/INDEX(CPI!$C:$C,MATCH(1960,CPI!$A:$A,0)))^(1/(2024-1960))-1 | H12: =MIN(Q_Fall)
B13: ="compound, 1960-2024, above inflation" | E13: ="World Bank, UK, same period" | H13: ="trough "&INDEX(Q_Label,MATCH(MIN(Q_Fall),Q_Fall,0))
B15: The big real-terms falls
B16: Episode | C16: Real fall from peak | E16: Trough
B17: 1970s oil shock (1973-1979) | C17: =_xlfn.MINIFS(Q_Fall,Q_Year,">=1973",Q_Year,"<=1979") | E17: =INDEX(Q_Label,MATCH(C17,Q_Fall,0))
B18: Early-1990s crash (1989-1996) | C18: =_xlfn.MINIFS(Q_Fall,Q_Year,">=1989",Q_Year,"<=1996") | E18: =INDEX(Q_Label,MATCH(C18,Q_Fall,0))
B19: Financial crisis (2007-2013) | C19: =_xlfn.MINIFS(Q_Fall,Q_Year,">=2007",Q_Year,"<=2013") | E19: =INDEX(Q_Label,MATCH(C19,Q_Fall,0))
B20: Fall from peak: real price against the highest real price reached before it. Cash prices fell far less in each episode, because inflation did part of the work.

Sheet Mortgage
B2: What did the average house cost a month?
B3: Repayment mortgage on the average Nationwide house in two quarters. Yellow cells are yours to change.
C5: Then | D5: Now | F5: Monthly repayment on the 'Now' house: rate x deposit
B6: Quarter | C6: 2007 Q3 | D6: 2024 Q4 | F6: Rate \ deposit | G6: 0.05 | H6: 0.1 | I6: 0.15 | J6: 0.2 | K6: 0.25
B7: Mortgage rate (your assumption) | C7: 0.05 | D7: 0.05 | F7: 0.02 | G7: =PMT($F7/12,$D$9*12,-$D$10*(1-G$6)) | H7: =PMT($F7/12,$D$9*12,-$D$10*(1-H$6)) | I7: =PMT($F7/12,$D$9*12,-$D$10*(1-I$6)) | J7: =PMT($F7/12,$D$9*12,-$D$10*(1-J$6)) | K7: =PMT($F7/12,$D$9*12,-$D$10*(1-K$6))
B8: Deposit | C8: 0.1 | D8: 0.1 | F8: 0.03 | G8: =PMT($F8/12,$D$9*12,-$D$10*(1-G$6)) | H8: =PMT($F8/12,$D$9*12,-$D$10*(1-H$6)) | I8: =PMT($F8/12,$D$9*12,-$D$10*(1-I$6)) | J8: =PMT($F8/12,$D$9*12,-$D$10*(1-J$6)) | K8: =PMT($F8/12,$D$9*12,-$D$10*(1-K$6))
B9: Term (years) | C9: 25 | D9: 25 | F9: 0.04 | G9: =PMT($F9/12,$D$9*12,-$D$10*(1-G$6)) | H9: =PMT($F9/12,$D$9*12,-$D$10*(1-H$6)) | I9: =PMT($F9/12,$D$9*12,-$D$10*(1-I$6)) | J9: =PMT($F9/12,$D$9*12,-$D$10*(1-J$6)) | K9: =PMT($F9/12,$D$9*12,-$D$10*(1-K$6))
B10: Average house price (£) | C10: =INDEX(Q_Price,MATCH(C6,Q_Label,0)) | D10: =INDEX(Q_Price,MATCH(D6,Q_Label,0)) | F10: 0.05 | G10: =PMT($F10/12,$D$9*12,-$D$10*(1-G$6)) | H10: =PMT($F10/12,$D$9*12,-$D$10*(1-H$6)) | I10: =PMT($F10/12,$D$9*12,-$D$10*(1-I$6)) | J10: =PMT($F10/12,$D$9*12,-$D$10*(1-J$6)) | K10: =PMT($F10/12,$D$9*12,-$D$10*(1-K$6))
B11: Deposit (£) | C11: =C10*C8 | D11: =D10*D8 | F11: 0.06 | G11: =PMT($F11/12,$D$9*12,-$D$10*(1-G$6)) | H11: =PMT($F11/12,$D$9*12,-$D$10*(1-H$6)) | I11: =PMT($F11/12,$D$9*12,-$D$10*(1-I$6)) | J11: =PMT($F11/12,$D$9*12,-$D$10*(1-J$6)) | K11: =PMT($F11/12,$D$9*12,-$D$10*(1-K$6))
B12: Loan (£) | C12: =C10-C11 | D12: =D10-D11 | F12: 0.07 | G12: =PMT($F12/12,$D$9*12,-$D$10*(1-G$6)) | H12: =PMT($F12/12,$D$9*12,-$D$10*(1-H$6)) | I12: =PMT($F12/12,$D$9*12,-$D$10*(1-I$6)) | J12: =PMT($F12/12,$D$9*12,-$D$10*(1-J$6)) | K12: =PMT($F12/12,$D$9*12,-$D$10*(1-K$6))
B13: Monthly rate | C13: =C7/12 | D13: =D7/12 | F13: 0.08 | G13: =PMT($F13/12,$D$9*12,-$D$10*(1-G$6)) | H13: =PMT($F13/12,$D$9*12,-$D$10*(1-H$6)) | I13: =PMT($F13/12,$D$9*12,-$D$10*(1-I$6)) | J13: =PMT($F13/12,$D$9*12,-$D$10*(1-J$6)) | K13: =PMT($F13/12,$D$9*12,-$D$10*(1-K$6))
B14: Monthly repayment (£) | C14: =PMT(C13,C9*12,-C12) | D14: =PMT(D13,D9*12,-D12)
B15: Total repaid over the term (£) | C15: =C14*C9*12 | D15: =D14*D9*12 | F15: Term from cell D9. Rates in column F are editable.
B16: Monthly repayment in base-year £ | C16: =IFERROR(C14*100/INDEX(CPI_Index,MATCH(VALUE(LEFT(C6,4)),CPI_Year,0)),"no inflation data yet") | D16: =IFERROR(D14*100/INDEX(CPI_Index,MATCH(VALUE(LEFT(D6,4)),CPI_Year,0)),"no inflation data yet")
B17: Deposit in base-year £ | C17: =IFERROR(C11*100/INDEX(CPI_Index,MATCH(VALUE(LEFT(C6,4)),CPI_Year,0)),"no inflation data yet") | D17: =IFERROR(D11*100/INDEX(CPI_Index,MATCH(VALUE(LEFT(D6,4)),CPI_Year,0)),"no inflation data yet")
B19: Change, then to now
B20: Monthly repayment, cash | C20: =D14/C14-1
B21: Monthly repayment, real (base-year £) | C21: =IFERROR(D16/C16-1,"needs inflation data for both quarters")
B22: Deposit, real (base-year £) | C22: =IFERROR(D17/C17-1,"needs inflation data for both quarters")

Sheet Annual
A1: One row per year (average of the year's quarters)
A2: Years with inflation data only, so cash and real prices can be compared.
A4: Year | B4: Average price (£) | C4: Real price (base-year £) | D4: Inflation | E4: Cash growth | F4: Real growth | G4: Real price vs 1960
A5: 1960 | B5: =AVERAGEIFS(Q_Price,Q_Year,A5) | C5: =AVERAGEIFS(Q_Real,Q_Year,A5) | D5: =INDEX(CPI!$B:$B,MATCH(A5,CPI!$A:$A,0)) | G5: =C5/$C$5
A6: 1961 | B6: =AVERAGEIFS(Q_Price,Q_Year,A6) | C6: =AVERAGEIFS(Q_Real,Q_Year,A6) | D6: =INDEX(CPI!$B:$B,MATCH(A6,CPI!$A:$A,0)) | E6: =B6/B5-1 | F6: =C6/C5-1 | G6: =C6/$C$5
A7: 1962 | B7: =AVERAGEIFS(Q_Price,Q_Year,A7) | C7: =AVERAGEIFS(Q_Real,Q_Year,A7) | D7: =INDEX(CPI!$B:$B,MATCH(A7,CPI!$A:$A,0)) | E7: =B7/B6-1 | F7: =C7/C6-1 | G7: =C7/$C$5
A8: 1963 | B8: =AVERAGEIFS(Q_Price,Q_Year,A8) | C8: =AVERAGEIFS(Q_Real,Q_Year,A8) | D8: =INDEX(CPI!$B:$B,MATCH(A8,CPI!$A:$A,0)) | E8: =B8/B7-1 | F8: =C8/C7-1 | G8: =C8/$C$5
A9: 1964 | B9: =AVERAGEIFS(Q_Price,Q_Year,A9) | C9: =AVERAGEIFS(Q_Real,Q_Year,A9) | D9: =INDEX(CPI!$B:$B,MATCH(A9,CPI!$A:$A,0)) | E9: =B9/B8-1 | F9: =C9/C8-1 | G9: =C9/$C$5
A10: 1965 | B10: =AVERAGEIFS(Q_Price,Q_Year,A10) | C10: =AVERAGEIFS(Q_Real,Q_Year,A10) | D10: =INDEX(CPI!$B:$B,MATCH(A10,CPI!$A:$A,0)) | E10: =B10/B9-1 | F10: =C10/C9-1 | G10: =C10/$C$5
A11: 1966 | B11: =AVERAGEIFS(Q_Price,Q_Year,A11) | C11: =AVERAGEIFS(Q_Real,Q_Year,A11) | D11: =INDEX(CPI!$B:$B,MATCH(A11,CPI!$A:$A,0)) | E11: =B11/B10-1 | F11: =C11/C10-1 | G11: =C11/$C$5
A12: 1967 | B12: =AVERAGEIFS(Q_Price,Q_Year,A12) | C12: =AVERAGEIFS(Q_Real,Q_Year,A12) | D12: =INDEX(CPI!$B:$B,MATCH(A12,CPI!$A:$A,0)) | E12: =B12/B11-1 | F12: =C12/C11-1 | G12: =C12/$C$5
A13: 1968 | B13: =AVERAGEIFS(Q_Price,Q_Year,A13) | C13: =AVERAGEIFS(Q_Real,Q_Year,A13) | D13: =INDEX(CPI!$B:$B,MATCH(A13,CPI!$A:$A,0)) | E13: =B13/B12-1 | F13: =C13/C12-1 | G13: =C13/$C$5
A14: 1969 | B14: =AVERAGEIFS(Q_Price,Q_Year,A14) | C14: =AVERAGEIFS(Q_Real,Q_Year,A14) | D14: =INDEX(CPI!$B:$B,MATCH(A14,CPI!$A:$A,0)) | E14: =B14/B13-1 | F14: =C14/C13-1 | G14: =C14/$C$5
A15: 1970 | B15: =AVERAGEIFS(Q_Price,Q_Year,A15) | C15: =AVERAGEIFS(Q_Real,Q_Year,A15) | D15: =INDEX(CPI!$B:$B,MATCH(A15,CPI!$A:$A,0)) | E15: =B15/B14-1 | F15: =C15/C14-1 | G15: =C15/$C$5
A16: 1971 | B16: =AVERAGEIFS(Q_Price,Q_Year,A16) | C16: =AVERAGEIFS(Q_Real,Q_Year,A16) | D16: =INDEX(CPI!$B:$B,MATCH(A16,CPI!$A:$A,0)) | E16: =B16/B15-1 | F16: =C16/C15-1 | G16: =C16/$C$5
A17: 1972 | B17: =AVERAGEIFS(Q_Price,Q_Year,A17) | C17: =AVERAGEIFS(Q_Real,Q_Year,A17) | D17: =INDEX(CPI!$B:$B,MATCH(A17,CPI!$A:$A,0)) | E17: =B17/B16-1 | F17: =C17/C16-1 | G17: =C17/$C$5
... A69: 2024 | B69: =AVERAGEIFS(Q_Price,Q_Year,A69) | C69: =AVERAGEIFS(Q_Real,Q_Year,A69) | D69: =INDEX(CPI!$B:$B,MATCH(A69,CPI!$A:$A,0)) | E69: =B69/B68-1 | F69: =C69/C68-1 | G69: =C69/$C$5

Sheet Decades
A1: Growth by decade
A2: First year of the decade against its last year (the 2020s run to 2024). Compound annual rate = (end / start)^(1 / years) - 1.
A4: Decade | B4: From | C4: To | D4: Cash price at start (£) | E4: Cash price at end (£) | F4: Cash growth | G4: Real growth | H4: Cash growth a year | I4: Real growth a year | J4: Average inflation a year
A5: 1960s | B5: 1960 | C5: =MIN(B5+9,MAX(A_Year)) | D5: =INDEX(A_Price,MATCH(B5,A_Year,0)) | E5: =INDEX(A_Price,MATCH(C5,A_Year,0)) | F5: =E5/D5-1 | G5: =INDEX(A_Real,MATCH(C5,A_Year,0))/INDEX(A_Real,MATCH(B5,A_Year,0))-1 | H5: =(1+F5)^(1/(C5-B5))-1 | I5: =(1+G5)^(1/(C5-B5))-1 | J5: =(INDEX(CPI!$C:$C,MATCH(C5,CPI!$A:$A,0))/INDEX(CPI!$C:$C,MATCH(B5,CPI!$A:$A,0)))^(1/(C5-B5))-1
A6: 1970s | B6: 1970 | C6: =MIN(B6+9,MAX(A_Year)) | D6: =INDEX(A_Price,MATCH(B6,A_Year,0)) | E6: =INDEX(A_Price,MATCH(C6,A_Year,0)) | F6: =E6/D6-1 | G6: =INDEX(A_Real,MATCH(C6,A_Year,0))/INDEX(A_Real,MATCH(B6,A_Year,0))-1 | H6: =(1+F6)^(1/(C6-B6))-1 | I6: =(1+G6)^(1/(C6-B6))-1 | J6: =(INDEX(CPI!$C:$C,MATCH(C6,CPI!$A:$A,0))/INDEX(CPI!$C:$C,MATCH(B6,CPI!$A:$A,0)))^(1/(C6-B6))-1
A7: 1980s | B7: 1980 | C7: =MIN(B7+9,MAX(A_Year)) | D7: =INDEX(A_Price,MATCH(B7,A_Year,0)) | E7: =INDEX(A_Price,MATCH(C7,A_Year,0)) | F7: =E7/D7-1 | G7: =INDEX(A_Real,MATCH(C7,A_Year,0))/INDEX(A_Real,MATCH(B7,A_Year,0))-1 | H7: =(1+F7)^(1/(C7-B7))-1 | I7: =(1+G7)^(1/(C7-B7))-1 | J7: =(INDEX(CPI!$C:$C,MATCH(C7,CPI!$A:$A,0))/INDEX(CPI!$C:$C,MATCH(B7,CPI!$A:$A,0)))^(1/(C7-B7))-1
A8: 1990s | B8: 1990 | C8: =MIN(B8+9,MAX(A_Year)) | D8: =INDEX(A_Price,MATCH(B8,A_Year,0)) | E8: =INDEX(A_Price,MATCH(C8,A_Year,0)) | F8: =E8/D8-1 | G8: =INDEX(A_Real,MATCH(C8,A_Year,0))/INDEX(A_Real,MATCH(B8,A_Year,0))-1 | H8: =(1+F8)^(1/(C8-B8))-1 | I8: =(1+G8)^(1/(C8-B8))-1 | J8: =(INDEX(CPI!$C:$C,MATCH(C8,CPI!$A:$A,0))/INDEX(CPI!$C:$C,MATCH(B8,CPI!$A:$A,0)))^(1/(C8-B8))-1
A9: 2000s | B9: 2000 | C9: =MIN(B9+9,MAX(A_Year)) | D9: =INDEX(A_Price,MATCH(B9,A_Year,0)) | E9: =INDEX(A_Price,MATCH(C9,A_Year,0)) | F9: =E9/D9-1 | G9: =INDEX(A_Real,MATCH(C9,A_Year,0))/INDEX(A_Real,MATCH(B9,A_Year,0))-1 | H9: =(1+F9)^(1/(C9-B9))-1 | I9: =(1+G9)^(1/(C9-B9))-1 | J9: =(INDEX(CPI!$C:$C,MATCH(C9,CPI!$A:$A,0))/INDEX(CPI!$C:$C,MATCH(B9,CPI!$A:$A,0)))^(1/(C9-B9))-1
A10: 2010s | B10: 2010 | C10: =MIN(B10+9,MAX(A_Year)) | D10: =INDEX(A_Price,MATCH(B10,A_Year,0)) | E10: =INDEX(A_Price,MATCH(C10,A_Year,0)) | F10: =E10/D10-1 | G10: =INDEX(A_Real,MATCH(C10,A_Year,0))/INDEX(A_Real,MATCH(B10,A_Year,0))-1 | H10: =(1+F10)^(1/(C10-B10))-1 | I10: =(1+G10)^(1/(C10-B10))-1 | J10: =(INDEX(CPI!$C:$C,MATCH(C10,CPI!$A:$A,0))/INDEX(CPI!$C:$C,MATCH(B10,CPI!$A:$A,0)))^(1/(C10-B10))-1
A11: 2020s | B11: 2020 | C11: =MIN(B11+9,MAX(A_Year)) | D11: =INDEX(A_Price,MATCH(B11,A_Year,0)) | E11: =INDEX(A_Price,MATCH(C11,A_Year,0)) | F11: =E11/D11-1 | G11: =INDEX(A_Real,MATCH(C11,A_Year,0))/INDEX(A_Real,MATCH(B11,A_Year,0))-1 | H11: =(1+F11)^(1/(C11-B11))-1 | I11: =(1+G11)^(1/(C11-B11))-1 | J11: =(INDEX(CPI!$C:$C,MATCH(C11,CPI!$A:$A,0))/INDEX(CPI!$C:$C,MATCH(B11,CPI!$A:$A,0)))^(1/(C11-B11))-1

Sheet Quarterly
A1: Nationwide quarters: cash price, real price and fall from the real peak
A2: Real price = cash price restated in base-year pounds. Fall from peak = real price against the highest real price reached so far.
A4: Date | B4: Year | C4: Quarter | D4: Label | E4: Average price, all houses (£) | F4: Average price, new houses (£) | G4: Price index (base = 100) | H4: Real price (base-year £) | I4: Change on a year earlier | J4: Real change on a year earlier | K4: Nationwide's published change | L4: Our change minus published (pp) | M4: Highest real price so far (£) | N4: Real fall from peak
A5: =Raw_Nationwide!A2 | B5: =YEAR(A5) | C5: ="Q"&ROUNDUP(MONTH(A5)/3,0) | D5: =B5&" "&C5 | E5: =Raw_Nationwide!B2 | F5: =Raw_Nationwide!D2 | G5: =IFERROR(INDEX(CPI_Index,MATCH(B5,CPI_Year,0)),"") | H5: =IF(G5="","",E5*100/G5) | K5: =IF(Raw_Nationwide!C2="","",Raw_Nationwide!C2/100) | M5: =IF(H5="","",MAX(H$5:H5)) | N5: =IF(H5="","",H5/M5-1)
A6: =Raw_Nationwide!A3 | B6: =YEAR(A6) | C6: ="Q"&ROUNDUP(MONTH(A6)/3,0) | D6: =B6&" "&C6 | E6: =Raw_Nationwide!B3 | F6: =Raw_Nationwide!D3 | G6: =IFERROR(INDEX(CPI_Index,MATCH(B6,CPI_Year,0)),"") | H6: =IF(G6="","",E6*100/G6) | K6: =IF(Raw_Nationwide!C3="","",Raw_Nationwide!C3/100) | M6: =IF(H6="","",MAX(H$5:H6)) | N6: =IF(H6="","",H6/M6-1)
A7: =Raw_Nationwide!A4 | B7: =YEAR(A7) | C7: ="Q"&ROUNDUP(MONTH(A7)/3,0) | D7: =B7&" "&C7 | E7: =Raw_Nationwide!B4 | F7: =Raw_Nationwide!D4 | G7: =IFERROR(INDEX(CPI_Index,MATCH(B7,CPI_Year,0)),"") | H7: =IF(G7="","",E7*100/G7) | K7: =IF(Raw_Nationwide!C4="","",Raw_Nationwide!C4/100) | M7: =IF(H7="","",MAX(H$5:H7)) | N7: =IF(H7="","",H7/M7-1)
A8: =Raw_Nationwide!A5 | B8: =YEAR(A8) | C8: ="Q"&ROUNDUP(MONTH(A8)/3,0) | D8: =B8&" "&C8 | E8: =Raw_Nationwide!B5 | F8: =Raw_Nationwide!D5 | G8: =IFERROR(INDEX(CPI_Index,MATCH(B8,CPI_Year,0)),"") | H8: =IF(G8="","",E8*100/G8) | K8: =IF(Raw_Nationwide!C5="","",Raw_Nationwide!C5/100) | M8: =IF(H8="","",MAX(H$5:H8)) | N8: =IF(H8="","",H8/M8-1)
A9: =Raw_Nationwide!A6 | B9: =YEAR(A9) | C9: ="Q"&ROUNDUP(MONTH(A9)/3,0) | D9: =B9&" "&C9 | E9: =Raw_Nationwide!B6 | F9: =Raw_Nationwide!D6 | G9: =IFERROR(INDEX(CPI_Index,MATCH(B9,CPI_Year,0)),"") | H9: =IF(G9="","",E9*100/G9) | I9: =E9/E5-1 | J9: =IF(OR(H9="",H5=""),"",H9/H5-1) | K9: =IF(Raw_Nationwide!C6="","",Raw_Nationwide!C6/100) | L9: =IF(K9="","",(I9-K9)*100) | M9: =IF(H9="","",MAX(H$5:H9)) | N9: =IF(H9="","",H9/M9-1)
A10: =Raw_Nationwide!A7 | B10: =YEAR(A10) | C10: ="Q"&ROUNDUP(MONTH(A10)/3,0) | D10: =B10&" "&C10 | E10: =Raw_Nationwide!B7 | F10: =Raw_Nationwide!D7 | G10: =IFERROR(INDEX(CPI_Index,MATCH(B10,CPI_Year,0)),"") | H10: =IF(G10="","",E10*100/G10) | I10: =E10/E6-1 | J10: =IF(OR(H10="",H6=""),"",H10/H6-1) | K10: =IF(Raw_Nationwide!C7="","",Raw_Nationwide!C7/100) | L10: =IF(K10="","",(I10-K10)*100) | M10: =IF(H10="","",MAX(H$5:H10)) | N10: =IF(H10="","",H10/M10-1)
A11: =Raw_Nationwide!A8 | B11: =YEAR(A11) | C11: ="Q"&ROUNDUP(MONTH(A11)/3,0) | D11: =B11&" "&C11 | E11: =Raw_Nationwide!B8 | F11: =Raw_Nationwide!D8 | G11: =IFERROR(INDEX(CPI_Index,MATCH(B11,CPI_Year,0)),"") | H11: =IF(G11="","",E11*100/G11) | I11: =E11/E7-1 | J11: =IF(OR(H11="",H7=""),"",H11/H7-1) | K11: =IF(Raw_Nationwide!C8="","",Raw_Nationwide!C8/100) | L11: =IF(K11="","",(I11-K11)*100) | M11: =IF(H11="","",MAX(H$5:H11)) | N11: =IF(H11="","",H11/M11-1)
A12: =Raw_Nationwide!A9 | B12: =YEAR(A12) | C12: ="Q"&ROUNDUP(MONTH(A12)/3,0) | D12: =B12&" "&C12 | E12: =Raw_Nationwide!B9 | F12: =Raw_Nationwide!D9 | G12: =IFERROR(INDEX(CPI_Index,MATCH(B12,CPI_Year,0)),"") | H12: =IF(G12="","",E12*100/G12) | I12: =E12/E8-1 | J12: =IF(OR(H12="",H8=""),"",H12/H8-1) | K12: =IF(Raw_Nationwide!C9="","",Raw_Nationwide!C9/100) | L12: =IF(K12="","",(I12-K12)*100) | M12: =IF(H12="","",MAX(H$5:H12)) | N12: =IF(H12="","",H12/M12-1)
A13: =Raw_Nationwide!A10 | B13: =YEAR(A13) | C13: ="Q"&ROUNDUP(MONTH(A13)/3,0) | D13: =B13&" "&C13 | E13: =Raw_Nationwide!B10 | F13: =Raw_Nationwide!D10 | G13: =IFERROR(INDEX(CPI_Index,MATCH(B13,CPI_Year,0)),"") | H13: =IF(G13="","",E13*100/G13) | I13: =E13/E9-1 | J13: =IF(OR(H13="",H9=""),"",H13/H9-1) | K13: =IF(Raw_Nationwide!C10="","",Raw_Nationwide!C10/100) | L13: =IF(K13="","",(I13-K13)*100) | M13: =IF(H13="","",MAX(H$5:H13)) | N13: =IF(H13="","",H13/M13-1)
A14: =Raw_Nationwide!A11 | B14: =YEAR(A14) | C14: ="Q"&ROUNDUP(MONTH(A14)/3,0) | D14: =B14&" "&C14 | E14: =Raw_Nationwide!B11 | F14: =Raw_Nationwide!D11 | G14: =IFERROR(INDEX(CPI_Index,MATCH(B14,CPI_Year,0)),"") | H14: =IF(G14="","",E14*100/G14) | I14: =E14/E10-1 | J14: =IF(OR(H14="",H10=""),"",H14/H10-1) | K14: =IF(Raw_Nationwide!C11="","",Raw_Nationwide!C11/100) | L14: =IF(K14="","",(I14-K14)*100) | M14: =IF(H14="","",MAX(H$5:H14)) | N14: =IF(H14="","",H14/M14-1)
A15: =Raw_Nationwide!A12 | B15: =YEAR(A15) | C15: ="Q"&ROUNDUP(MONTH(A15)/3,0) | D15: =B15&" "&C15 | E15: =Raw_Nationwide!B12 | F15: =Raw_Nationwide!D12 | G15: =IFERROR(INDEX(CPI_Index,MATCH(B15,CPI_Year,0)),"") | H15: =IF(G15="","",E15*100/G15) | I15: =E15/E11-1 | J15: =IF(OR(H15="",H11=""),"",H15/H11-1) | K15: =IF(Raw_Nationwide!C12="","",Raw_Nationwide!C12/100) | L15: =IF(K15="","",(I15-K15)*100) | M15: =IF(H15="","",MAX(H$5:H15)) | N15: =IF(H15="","",H15/M15-1)
A16: =Raw_Nationwide!A13 | B16: =YEAR(A16) | C16: ="Q"&ROUNDUP(MONTH(A16)/3,0) | D16: =B16&" "&C16 | E16: =Raw_Nationwide!B13 | F16: =Raw_Nationwide!D13 | G16: =IFERROR(INDEX(CPI_Index,MATCH(B16,CPI_Year,0)),"") | H16: =IF(G16="","",E16*100/G16) | I16: =E16/E12-1 | J16: =IF(OR(H16="",H12=""),"",H16/H12-1) | K16: =IF(Raw_Nationwide!C13="","",Raw_Nationwide!C13/100) | L16: =IF(K16="","",(I16-K16)*100) | M16: =IF(H16="","",MAX(H$5:H16)) | N16: =IF(H16="","",H16/M16-1)
A17: =Raw_Nationwide!A14 | B17: =YEAR(A17) | C17: ="Q"&ROUNDUP(MONTH(A17)/3,0) | D17: =B17&" "&C17 | E17: =Raw_Nationwide!B14 | F17: =Raw_Nationwide!D14 | G17: =IFERROR(INDEX(CPI_Index,MATCH(B17,CPI_Year,0)),"") | H17: =IF(G17="","",E17*100/G17) | I17: =E17/E13-1 | J17: =IF(OR(H17="",H13=""),"",H17/H13-1) | K17: =IF(Raw_Nationwide!C14="","",Raw_Nationwide!C14/100) | L17: =IF(K17="","",(I17-K17)*100) | M17: =IF(H17="","",MAX(H$5:H17)) | N17: =IF(H17="","",H17/M17-1)
A18: =Raw_Nationwide!A15 | B18: =YEAR(A18) | C18: ="Q"&ROUNDUP(MONTH(A18)/3,0) | D18: =B18&" "&C18 | E18: =Raw_Nationwide!B15 | F18: =Raw_Nationwide!D15 | G18: =IFERROR(INDEX(CPI_Index,MATCH(B18,CPI_Year,0)),"") | H18: =IF(G18="","",E18*100/G18) | I18: =E18/E14-1 | J18: =IF(OR(H18="",H14=""),"",H18/H14-1) | K18: =IF(Raw_Nationwide!C15="","",Raw_Nationwide!C15/100) | L18: =IF(K18="","",(I18-K18)*100) | M18: =IF(H18="","",MAX(H$5:H18)) | N18: =IF(H18="","",H18/M18-1)
A19: =Raw_Nationwide!A16 | B19: =YEAR(A19) | C19: ="Q"&ROUNDUP(MONTH(A19)/3,0) | D19: =B19&" "&C19 | E19: =Raw_Nationwide!B16 | F19: =Raw_Nationwide!D16 | G19: =IFERROR(INDEX(CPI_Index,MATCH(B19,CPI_Year,0)),"") | H19: =IF(G19="","",E19*100/G19) | I19: =E19/E15-1 | J19: =IF(OR(H19="",H15=""),"",H19/H15-1) | K19: =IF(Raw_Nationwide!C16="","",Raw_Nationwide!C16/100) | L19: =IF(K19="","",(I19-K19)*100) | M19: =IF(H19="","",MAX(H$5:H19)) | N19: =IF(H19="","",H19/M19-1)
A20: =Raw_Nationwide!A17 | B20: =YEAR(A20) | C20: ="Q"&ROUNDUP(MONTH(A20)/3,0) | D20: =B20&" "&C20 | E20: =Raw_Nationwide!B17 | F20: =Raw_Nationwide!D17 | G20: =IFERROR(INDEX(CPI_Index,MATCH(B20,CPI_Year,0)),"") | H20: =IF(G20="","",E20*100/G20) | I20: =E20/E16-1 | J20: =IF(OR(H20="",H16=""),"",H20/H16-1) | K20: =IF(Raw_Nationwide!C17="","",Raw_Nationwide!C17/100) | L20: =IF(K20="","",(I20-K20)*100) | M20: =IF(H20="","",MAX(H$5:H20)) | N20: =IF(H20="","",H20/M20-1)
... A294: =Raw_Nationwide!A291 | B294: =YEAR(A294) | C294: ="Q"&ROUNDUP(MONTH(A294)/3,0) | D294: =B294&" "&C294 | E294: =Raw_Nationwide!B291 | F294: =Raw_Nationwide!D291 | G294: =IFERROR(INDEX(CPI_Index,MATCH(B294,CPI_Year,0)),"") | H294: =IF(G294="","",E294*100/G294) | I294: =E294/E290-1 | J294: =IF(OR(H294="",H290=""),"",H294/H290-1) | K294: =IF(Raw_Nationwide!C291="","",Raw_Nationwide!C291/100) | L294: =IF(K294="","",(I294-K294)*100) | M294: =IF(H294="","",MAX(H$5:H294)) | N294: =IF(H294="","",H294/M294-1)

Sheet CPI
A1: UK price level, chained from the World Bank's annual inflation
A2: Index: 1959 = 100, then each year = previous x (1 + inflation). Rebased: base year = 100 (base year set on the Dashboard).
A4: Year | B4: Inflation (World Bank, %) | C4: Price index (1959 = 100) | D4: Index (base year = 100) | E4: Rows found
A5: 1959 | C5: 100 | D5: =C5/INDEX($C$5:$C$70,MATCH(BaseYear,$A$5:$A$70,0))*100
A6: 1960 | B6: =SUMIFS(Raw_CPI!$D:$D,Raw_CPI!$B:$B,"GBR",Raw_CPI!$C:$C,A6)/100 | C6: =C5*(1+B6) | D6: =C6/INDEX($C$5:$C$70,MATCH(BaseYear,$A$5:$A$70,0))*100 | E6: =COUNTIFS(Raw_CPI!$B:$B,"GBR",Raw_CPI!$C:$C,A6)
A7: 1961 | B7: =SUMIFS(Raw_CPI!$D:$D,Raw_CPI!$B:$B,"GBR",Raw_CPI!$C:$C,A7)/100 | C7: =C6*(1+B7) | D7: =C7/INDEX($C$5:$C$70,MATCH(BaseYear,$A$5:$A$70,0))*100 | E7: =COUNTIFS(Raw_CPI!$B:$B,"GBR",Raw_CPI!$C:$C,A7)
A8: 1962 | B8: =SUMIFS(Raw_CPI!$D:$D,Raw_CPI!$B:$B,"GBR",Raw_CPI!$C:$C,A8)/100 | C8: =C7*(1+B8) | D8: =C8/INDEX($C$5:$C$70,MATCH(BaseYear,$A$5:$A$70,0))*100 | E8: =COUNTIFS(Raw_CPI!$B:$B,"GBR",Raw_CPI!$C:$C,A8)
A9: 1963 | B9: =SUMIFS(Raw_CPI!$D:$D,Raw_CPI!$B:$B,"GBR",Raw_CPI!$C:$C,A9)/100 | C9: =C8*(1+B9) | D9: =C9/INDEX($C$5:$C$70,MATCH(BaseYear,$A$5:$A$70,0))*100 | E9: =COUNTIFS(Raw_CPI!$B:$B,"GBR",Raw_CPI!$C:$C,A9)
A10: 1964 | B10: =SUMIFS(Raw_CPI!$D:$D,Raw_CPI!$B:$B,"GBR",Raw_CPI!$C:$C,A10)/100 | C10: =C9*(1+B10) | D10: =C10/INDEX($C$5:$C$70,MATCH(BaseYear,$A$5:$A$70,0))*100 | E10: =COUNTIFS(Raw_CPI!$B:$B,"GBR",Raw_CPI!$C:$C,A10)
A11: 1965 | B11: =SUMIFS(Raw_CPI!$D:$D,Raw_CPI!$B:$B,"GBR",Raw_CPI!$C:$C,A11)/100 | C11: =C10*(1+B11) | D11: =C11/INDEX($C$5:$C$70,MATCH(BaseYear,$A$5:$A$70,0))*100 | E11: =COUNTIFS(Raw_CPI!$B:$B,"GBR",Raw_CPI!$C:$C,A11)
A12: 1966 | B12: =SUMIFS(Raw_CPI!$D:$D,Raw_CPI!$B:$B,"GBR",Raw_CPI!$C:$C,A12)/100 | C12: =C11*(1+B12) | D12: =C12/INDEX($C$5:$C$70,MATCH(BaseYear,$A$5:$A$70,0))*100 | E12: =COUNTIFS(Raw_CPI!$B:$B,"GBR",Raw_CPI!$C:$C,A12)
A13: 1967 | B13: =SUMIFS(Raw_CPI!$D:$D,Raw_CPI!$B:$B,"GBR",Raw_CPI!$C:$C,A13)/100 | C13: =C12*(1+B13) | D13: =C13/INDEX($C$5:$C$70,MATCH(BaseYear,$A$5:$A$70,0))*100 | E13: =COUNTIFS(Raw_CPI!$B:$B,"GBR",Raw_CPI!$C:$C,A13)
A14: 1968 | B14: =SUMIFS(Raw_CPI!$D:$D,Raw_CPI!$B:$B,"GBR",Raw_CPI!$C:$C,A14)/100 | C14: =C13*(1+B14) | D14: =C14/INDEX($C$5:$C$70,MATCH(BaseYear,$A$5:$A$70,0))*100 | E14: =COUNTIFS(Raw_CPI!$B:$B,"GBR",Raw_CPI!$C:$C,A14)
A15: 1969 | B15: =SUMIFS(Raw_CPI!$D:$D,Raw_CPI!$B:$B,"GBR",Raw_CPI!$C:$C,A15)/100 | C15: =C14*(1+B15) | D15: =C15/INDEX($C$5:$C$70,MATCH(BaseYear,$A$5:$A$70,0))*100 | E15: =COUNTIFS(Raw_CPI!$B:$B,"GBR",Raw_CPI!$C:$C,A15)
A16: 1970 | B16: =SUMIFS(Raw_CPI!$D:$D,Raw_CPI!$B:$B,"GBR",Raw_CPI!$C:$C,A16)/100 | C16: =C15*(1+B16) | D16: =C16/INDEX($C$5:$C$70,MATCH(BaseYear,$A$5:$A$70,0))*100 | E16: =COUNTIFS(Raw_CPI!$B:$B,"GBR",Raw_CPI!$C:$C,A16)
A17: 1971 | B17: =SUMIFS(Raw_CPI!$D:$D,Raw_CPI!$B:$B,"GBR",Raw_CPI!$C:$C,A17)/100 | C17: =C16*(1+B17) | D17: =C17/INDEX($C$5:$C$70,MATCH(BaseYear,$A$5:$A$70,0))*100 | E17: =COUNTIFS(Raw_CPI!$B:$B,"GBR",Raw_CPI!$C:$C,A17)
... A70: 2024 | B70: =SUMIFS(Raw_CPI!$D:$D,Raw_CPI!$B:$B,"GBR",Raw_CPI!$C:$C,A70)/100 | C70: =C69*(1+B70) | D70: =C70/INDEX($C$5:$C$70,MATCH(BaseYear,$A$5:$A$70,0))*100 | E70: =COUNTIFS(Raw_CPI!$B:$B,"GBR",Raw_CPI!$C:$C,A70)

Sheet Checks
A1: Reconciliation checks
A2: Each test compares the calculation sheets with the raw data. PASS or FAIL updates with every recalculation.
A4: Check | B4: Result | C4: Status | D4: What it proves
A5: Quarters in the calculation = rows in the raw file | B5: =COUNT(Q_Price)&" of "&COUNT(Raw_Nationwide!B:B) | C5: =IF(COUNT(Q_Price)=COUNT(Raw_Nationwide!B:B),"PASS","FAIL") | D5: No quarter dropped or duplicated.
A6: Sum of cash prices = sum in the raw file | B6: =SUM(Q_Price)-SUM(Raw_Nationwide!B:B) | C6: =IF(ABS(B6)<0.5,"PASS","FAIL") | D6: The calculation reads every price unchanged.
A7: Largest gap between our year-on-year change and Nationwide's (pp) | B7: =MAX(MAX(Q_Diff),-MIN(Q_Diff)) | C7: =IF(B7<0.1,"PASS","FAIL") | D7: Our change formula reproduces Nationwide's published figure to within rounding (0.1 percentage points).
A8: UK inflation years found once each in the raw CPI file | B8: =SUM(CPI!E6:E70)&" of 65" | C8: =IF(AND(SUM(CPI!E6:E70)=65,MAX(CPI!E6:E70)=1),"PASS","FAIL") | D8: Every year from 1960 matches exactly one World Bank row for the UK.
A9: Price index in the base year = 100 | B9: =INDEX(CPI_Index,MATCH(BaseYear,CPI_Year,0)) | C9: =IF(ABS(B9-100)<0.000001,"PASS","FAIL") | D9: Real prices are in base-year pounds.
A10: Real price = cash price in the base year | B10: =INDEX(A_Real,MATCH(BaseYear,A_Year,0))-INDEX(A_Price,MATCH(BaseYear,A_Year,0)) | C10: =IF(ABS(B10)<0.5,"PASS","FAIL") | D10: Deflating is consistent: in the base year, nothing changes.
A11: Quarters with a real price | B11: =COUNT(Q_Real) | C11: =IF(COUNT(Q_Real)=COUNTIFS(Q_Year,">=1960",Q_Year,"<=2024"),"PASS","FAIL") | D11: Every quarter from 1960 to 2024 has a real price; later quarters are left blank on purpose.
A12: Mortgage payment check | B12: =Mortgage!C14*Mortgage!C9*12-Mortgage!C12 | C12: =IF(B12>0,"PASS","FAIL") | D12: Total repaid over the term is more than the loan, so the PMT signs are right.

Sheet Raw_Nationwide
A1: Date | B1: Price (All) | C1: Change (All) | D1: Price (New) | E1: Change (New) | F1: Price (Modern) | G1: Change (Modern) | H1: Price (Older) | I1: Change (Older)
A2: 19391 | B2: 1891 | D2: 2107 | F2: 2002 | H2: 1542
A3: 19480 | B3: 1891 | D3: 2107 | F3: 2002 | H3: 1542
A4: 19572 | B4: 1881 | D4: 2117 | F4: 2002 | H4: 1524
A5: 19664 | B5: 1872 | C5: -1 | D5: 2117 | E5: 0.5 | F5: 1975 | G5: -2.2 | H5: 1542 | I5: 1.2
A6: 19756 | B6: 1863 | C6: -1.5 | D6: 2117 | E6: 0.5 | F6: 1957 | G6: -2.2 | H6: 1524 | I6: -1.2
A7: 19845 | B7: 1872 | C7: -1 | D7: 2117 | E7: 0.5 | F7: 1984 | G7: -0.9 | H7: 1515 | I7: -1.7
A8: 19937 | B8: 1863 | C8: -1 | D8: 2127 | E8: 0.5 | F8: 1948 | G8: -2.7 | H8: 1524 | I8: 0
A9: 20029 | B9: 1853 | C9: -1 | D9: 2127 | E9: 0.5 | F9: 1939 | G9: -1.8 | H9: 1515 | I9: -1.7
A10: 20121 | B10: 1900 | C10: 2 | D10: 2167 | E10: 2.4 | F10: 1984 | G10: 1.4 | H10: 1569 | I10: 2.9
A11: 20210 | B11: 1937 | C11: 3.5 | D11: 2217 | E11: 4.8 | F11: 2037 | G11: 2.7 | H11: 1578 | I11: 4.1
A12: 20302 | B12: 1937 | C12: 4 | D12: 2217 | E12: 4.3 | F12: 2037 | G12: 4.6 | H12: 1587 | I12: 4.1
A13: 20394 | B13: 1937 | C13: 4.5 | D13: 2217 | E13: 4.3 | F13: 2029 | G13: 4.6 | H13: 1587 | I13: 4.7
A14: 20486 | B14: 1975 | C14: 3.9 | D14: 2278 | E14: 5.1 | F14: 2082 | G14: 5 | H14: 1596 | I14: 1.7
A15: 20576 | B15: 2003 | C15: 3.4 | D15: 2318 | E15: 4.5 | F15: 2109 | G15: 3.5 | H15: 1631 | I15: 3.4
A16: 20668 | B16: 2003 | C16: 3.4 | D16: 2318 | E16: 4.5 | F16: 2109 | G16: 3.5 | H16: 1631 | I16: 2.8
... A251: 42125 | B251: 194258 | C251: 4.1 | D251: 194511 | E251: 2.3 | F251: 179358 | G251: 4.5 | H251: 201008 | I251: 4.6
A252: 42217 | B252: 195733 | C252: 3.7 | D252: 202250 | E252: 4.6 | F252: 0 | H252: 0
A253: 42309 | B253: 197044 | C253: 4.3 | D253: 203122 | E253: 3.6
A254: 42401 | B254: 198564 | C254: 5.3 | D254: 210093 | E254: 9.2
A255: 42491 | B255: 204238 | C255: 5.1 | D255: 214987 | E255: 10.5
A256: 42583 | B256: 206346 | C256: 5.4 | D256: 219881 | E256: 8.7
A257: 42675 | B257: 205937 | C257: 4.5 | D257: 218725 | E257: 7.7
A258: 42767 | B258: 206665 | C258: 4.1 | D258: 216824 | E258: 3.2
A259: 42856 | B259: 209971 | C259: 2.8 | D259: 223315 | E259: 3.9
A260: 42948 | B260: 211672 | C260: 2.6 | D260: 224273 | E260: 2
A261: 43040 | B261: 211433 | C261: 2.7 | D261: 233723 | E261: 6.9
A262: 43132 | B262: 211792 | C262: 2.5 | D262: 233116 | E262: 7.5
A263: 43221 | B263: 214578 | C263: 2.2 | D263: 230698 | E263: 3.3
A264: 43313 | B264: 216103 | C264: 2.1 | D264: 233214 | E264: 4
... A291: 45778 | B291: 272751 | C291: 2.9 | D291: 313238 | E291: 5

Sheet Raw_CPI
A1: Country | B1: Country Code | C1: Year | D1: CPI
A2: Aruba | B2: ABW | C2: 1985 | D2: 4.0322581
A3: Aruba | B3: ABW | C3: 1986 | D3: 1.0739664
A4: Aruba | B4: ABW | C4: 1987 | D4: 3.6430455
A5: Aruba | B5: ABW | C5: 1988 | D5: 3.1218685
A6: Aruba | B6: ABW | C6: 1989 | D6: 3.991628
A7: Aruba | B7: ABW | C7: 1990 | D7: 5.8366878
A8: Aruba | B8: ABW | C8: 1991 | D8: 5.5555556
A9: Aruba | B9: ABW | C9: 1992 | D9: 3.8733754
A10: Aruba | B10: ABW | C10: 1993 | D10: 5.21556
A11: Aruba | B11: ABW | C11: 1994 | D11: 6.3110797
A12: Aruba | B12: ABW | C12: 1995 | D12: 3.3613911
A13: Aruba | B13: ABW | C13: 1996 | D13: 3.225288
... A11183: Zimbabwe | B11183: ZWE | C11183: 2022 | D11183: 104.70517
